{
    "default": {
        "revision": "master",
        "local_path": "subrepos"
    },
    "list": [
        {
            "repo_path": "git@github.com:DavidRbrt/dev-tools.git",
            "revision": "f303925686fc87ab2547bfee691d1d8be00f4b71",
            "local_path": "subrepos/yoyoyo"
        },
        {
            "repo_path": "git@github.com:DavidRbrt/lookup-table-generator.git",
            "revision": "798a91585f3ad29a9c28cad8a3c35ee725538aed",
            "local_path": "subrepos"
        }
    ]
}
